baseImage/__init__.py
baseImage/base_image.py
baseImage/base_image.pyi
baseImage/constant.py
baseImage/coordinate.py
baseImage/exceptions.py
baseImage/utils/__init__.py
baseImage/utils/api.py
baseImage/utils/api.pyi
baseImage/utils/image_diff/__init__.py
baseImage/utils/image_diff/ssim_diff.py
baseImage/utils/ssim/__init__.py
baseImage/utils/ssim/paddle.py
baseImage/utils/ssim/ssim.py
tests/__init__.py
tests/test_all.py
baseImage-2.1.5.dist-info/LICENSE
baseImage-2.1.5.dist-info/METADATA
baseImage-2.1.5.dist-info/WHEEL
baseImage-2.1.5.dist-info/top_level.txt
baseImage-2.1.5.dist-info/RECORD
