Metadata-Version: 2.1
Name: baseImage
Version: 2.1.5
Summary: This is a secondary package of OpenCV,for manage image data
Home-page: https://github.com/hakaboom/base_image
Author: hakaboom
Author-email: 1534225986@qq.com
License: Apache License 2.0
Classifier: Programming Language :: Python :: 3.6
Classifier: Programming Language :: Python :: 3.7
Classifier: Programming Language :: Python :: 3.8
Classifier: Programming Language :: Python :: 3.9
Classifier: Programming Language :: Python :: 3.10
Classifier: License :: OSI Approved :: Apache Software License
Classifier: Operating System :: OS Independent
Requires-Python: >=3.6, <3.11
License-File: LICENSE
Requires-Dist: numpy
Requires-Dist: opencv-python >=4.5.5.64
Requires-Dist: pydantic
